kipu_quantum_hub_mcp/__init__.py
kipu_quantum_hub_mcp/server.py
kipu_quantum_hub_mcp-0.1.1.dist-info/METADATA
kipu_quantum_hub_mcp-0.1.1.dist-info/WHEEL
kipu_quantum_hub_mcp-0.1.1.dist-info/entry_points.txt
kipu_quantum_hub_mcp-0.1.1.dist-info/RECORD
