Metadata-Version: 2.4
Name: kipu-quantum-hub-mcp
Version: 0.1.1
Summary: Kipu Quantum Hub MCP Server
Requires-Python: >=3.12
Requires-Dist: build>=1.3.0
Requires-Dist: fastmcp>=2.9.2
Requires-Dist: planqk-api-sdk>=1.3.7
Requires-Dist: planqk-quantum-client>=1.1.0
Requires-Dist: planqk-quantum>=2.22.0
Requires-Dist: planqk-service-sdk>=2.8.0
